simple_regional/__init__.py
simple_regional/one_spatial_scale.py
simple_regional/utils.py
simple_regional-1.0.1.dist-info/LICENSE
simple_regional-1.0.1.dist-info/METADATA
simple_regional-1.0.1.dist-info/WHEEL
simple_regional-1.0.1.dist-info/top_level.txt
simple_regional-1.0.1.dist-info/RECORD
